Metadata-Version: 1.0
Name: digimarks
Version: 1.1.0
Summary: Simple bookmarking service, using a SQLite database to store bookmarks, supporting tags and automatic title fetching.
Home-page: https://github.com/aquatix/digimarks
Author: Michiel Scholten
Author-email: michiel@diginaut.net
License: Apache
Platform: UNKNOWN
